redshift_sqlalchemy/__init__.py
sqlalchemy_redshift/__init__.py
sqlalchemy_redshift/commands.py
sqlalchemy_redshift/ddl.py
sqlalchemy_redshift/dialect.py
sqlalchemy_redshift/redshift-ca-bundle.crt
chalk_sqlalchemy_redshift-0.8.15.dev0.dist-info/METADATA
chalk_sqlalchemy_redshift-0.8.15.dev0.dist-info/WHEEL
chalk_sqlalchemy_redshift-0.8.15.dev0.dist-info/entry_points.txt
chalk_sqlalchemy_redshift-0.8.15.dev0.dist-info/top_level.txt
chalk_sqlalchemy_redshift-0.8.15.dev0.dist-info/RECORD
