Metadata-Version: 2.4
Name: chalk-sqlalchemy-redshift
Version: 0.8.15.dev0
Summary: Amazon Redshift Dialect for sqlalchemy (Chalk fork)
Home-page: https://github.com/chalk-ai/sqlalchemy-redshift
Author: Matt George
Author-email: mgeorge@gmail.com
Maintainer: Chalk
Maintainer-email: support@chalk.ai
License: MIT
Classifier: Development Status :: 4 - Beta
Classifier: Environment :: Console
Classifier: Intended Audience :: Developers
Classifier: License :: OSI Approved :: MIT License
Classifier: Operating System :: OS Independent
Classifier: Programming Language :: Python
Classifier: Programming Language :: Python :: 3
Classifier: Programming Language :: Python :: 3.8
Classifier: Programming Language :: Python :: 3.9
Classifier: Programming Language :: Python :: 3.10
Classifier: Programming Language :: Python :: 3.11
Classifier: Programming Language :: Python :: 3.12
Requires-Python: >=3.8
Requires-Dist: SQLAlchemy<2.0.0,>=0.9.2
Requires-Dist: packaging
Dynamic: author
Dynamic: author-email
Dynamic: classifier
Dynamic: description
Dynamic: description-content-type
Dynamic: home-page
Dynamic: license
Dynamic: maintainer
Dynamic: maintainer-email
Dynamic: requires-dist
Dynamic: requires-python
Dynamic: summary
